bioreadout/__init__.py
bioreadout/_efo.py
bioreadout/_lookup.py
bioreadout-0.2.1.dist-info/LICENSE
bioreadout-0.2.1.dist-info/WHEEL
bioreadout-0.2.1.dist-info/METADATA
bioreadout-0.2.1.dist-info/RECORD
