Metadata-Version: 2.1
Name: bioreadout
Version: 0.2.1
Summary: Bio file readers, instrument schema.
Author-email: Lamin Labs <laminlabs@gmail.com>
Requires-Dist: nbproject
Requires-Dist: bionty>=0.4.0
Requires-Dist: pre-commit ; extra == "dev"
Requires-Dist: nox ; extra == "dev"
Requires-Dist: pytest>=6.0 ; extra == "test"
Requires-Dist: pytest-cov ; extra == "test"
Project-URL: Home, https://github.com/laminlabs/bioreadout
Provides-Extra: dev
Provides-Extra: test
